vbdataset/__init__.py
vbdataset/fetch.py
vbdataset-0.0.1.dist-info/METADATA
vbdataset-0.0.1.dist-info/WHEEL
vbdataset-0.0.1.dist-info/top_level.txt
vbdataset-0.0.1.dist-info/RECORD
